moban_ansible/__init__.py
moban_ansible/_version.py
moban_ansible/engines/__init__.py
moban_ansible/engines/line_in_file.py
moban_ansible/tests/__init__.py
moban_ansible/tests/files.py
moban_ansible/tests/win32.py
moban_ansible-0.0.2.dist-info/LICENSE
moban_ansible-0.0.2.dist-info/METADATA
moban_ansible-0.0.2.dist-info/WHEEL
moban_ansible-0.0.2.dist-info/top_level.txt
moban_ansible-0.0.2.dist-info/RECORD
