Metadata-Version: 2.1
Name: moban-ansible
Version: 0.0.2
Summary: Ansible filters, tests and utility functions for moban users
Home-page: https://github.com/moremoban/moban-ansible
Author: chfw
Author-email: info@moremoban.org
License: newbsd
Download-URL: https://github.com/moremoban/moban-ansible/archive/0.0.2.tar.gz
Keywords: python
Platform: UNKNOWN
Classifier: Topic :: Software Development :: Libraries
Classifier: Programming Language :: Python
Classifier: Intended Audience :: Developers
Classifier: Programming Language :: Python :: 2.6
Classifier: Programming Language :: Python :: 2.7
Classifier: Programming Language :: Python :: 3.3
Classifier: Programming Language :: Python :: 3.4
Classifier: Programming Language :: Python :: 3.5
Classifier: Programming Language :: Python :: 3.6
Classifier: Programming Language :: Python :: 3.7
Classifier: Programming Language :: Python :: 3.8
Requires-Dist: moban (>=0.8.1)
